meteoroid_cli/__init__.py
meteoroid_cli/main.py
meteoroid_cli/meteoroid/__init__.py
meteoroid_cli/meteoroid/v1/__init__.py
meteoroid_cli/meteoroid/v1/endpoint.py
meteoroid_cli/meteoroid/v1/errors.py
meteoroid_cli/meteoroid/v1/function.py
meteoroid_cli/meteoroid/v1/result.py
meteoroid_cli/meteoroid/v1/schedule.py
meteoroid_cli/meteoroid/v1/subscription.py
meteoroid_cli/meteoroid/v1/client/__init__.py
meteoroid_cli/meteoroid/v1/client/base.py
meteoroid_cli/meteoroid/v1/client/endpoint_client.py
meteoroid_cli/meteoroid/v1/client/function_client.py
meteoroid_cli/meteoroid/v1/client/result_client.py
meteoroid_cli/meteoroid/v1/client/schedule_client.py
meteoroid_cli/meteoroid/v1/client/subscription_client.py
meteoroid_cli/meteoroid/v1/libs/__init__.py
meteoroid_cli/meteoroid/v1/libs/decorator.py
meteoroid_cli-1.0.2.dist-info/AUTHORS
meteoroid_cli-1.0.2.dist-info/LICENSE
meteoroid_cli-1.0.2.dist-info/METADATA
meteoroid_cli-1.0.2.dist-info/WHEEL
meteoroid_cli-1.0.2.dist-info/entry_points.txt
meteoroid_cli-1.0.2.dist-info/pbr.json
meteoroid_cli-1.0.2.dist-info/top_level.txt
meteoroid_cli-1.0.2.dist-info/RECORD
